{
	"backtrace" : 3,
	"backtraceGraph" : 
	{
		"commands" : 
		[
			"add_custom_target",
			"include",
			"add_custom_command"
		],
		"files" : 
		[
			"cmake/luajit/LuaJIT.cmake",
			"CMakeLists.txt"
		],
		"nodes" : 
		[
			{
				"file" : 1
			},
			{
				"command" : 1,
				"file" : 1,
				"line" : 72,
				"parent" : 0
			},
			{
				"file" : 0,
				"parent" : 1
			},
			{
				"command" : 0,
				"file" : 0,
				"line" : 410,
				"parent" : 2
			},
			{
				"command" : 2,
				"file" : 0,
				"line" : 394,
				"parent" : 2
			}
		]
	},
	"dependencies" : 
	[
		{
			"backtrace" : 4,
			"id" : "buildvm::@24c116b262c94e2133a9"
		}
	],
	"id" : "lj_gen_headers::@6890427a1f51a3e7e1df",
	"name" : "lj_gen_headers",
	"paths" : 
	{
		"build" : ".",
		"source" : "."
	},
	"sourceGroups" : 
	[
		{
			"name" : "",
			"sourceIndexes" : 
			[
				0
			]
		},
		{
			"name" : "CMake Rules",
			"sourceIndexes" : 
			[
				1,
				2
			]
		}
	],
	"sources" : 
	[
		{
			"backtrace" : 3,
			"isGenerated" : true,
			"path" : "out/build/x64-Debug/CMakeFiles/lj_gen_headers",
			"sourceGroupIndex" : 0
		},
		{
			"backtrace" : 0,
			"isGenerated" : true,
			"path" : "out/build/x64-Debug/CMakeFiles/lj_gen_headers.rule",
			"sourceGroupIndex" : 1
		},
		{
			"backtrace" : 0,
			"isGenerated" : true,
			"path" : "out/build/x64-Debug/lj_libdef.h.rule",
			"sourceGroupIndex" : 1
		}
	],
	"type" : "UTILITY"
}
